nutritiontools/__init__.py
nutritiontools/semantic.py
semanticjoshuadrc-0.0.1.dist-info/LICENSE.txt
semanticjoshuadrc-0.0.1.dist-info/METADATA
semanticjoshuadrc-0.0.1.dist-info/WHEEL
semanticjoshuadrc-0.0.1.dist-info/top_level.txt
semanticjoshuadrc-0.0.1.dist-info/RECORD
