Metadata-Version: 2.1
Name: semanticjoshuadrc
Version: 0.0.1
Summary: Tools for semantic nutrition
Home-page: https://github.com/pypa/sampleproject
Author: Joshua D'Arcy
Author-email: joshuadrc@gmail.com
License: UNKNOWN
Platform: UNKNOWN
Classifier: Programming Language :: Python :: 3
Classifier: License :: OSI Approved :: MIT License
Classifier: Operating System :: OS Independent
Requires-Python: >=3.6
